valphi/__init__.py
valphi/__main__.py
valphi/cli.py
valphi/contexts.py
valphi/controllers.py
valphi/models.py
valphi/networks.py
valphi/propagators.py
valphi/utils.py
valphi-0.6.0.dist-info/LICENSE
valphi-0.6.0.dist-info/METADATA
valphi-0.6.0.dist-info/WHEEL
valphi-0.6.0.dist-info/RECORD
