Metadata-Version: 2.1
Name: valphi
Version: 0.6.0
Summary: Logic programs ralying on ValPhi semantics
Author: Mario Alviano
Author-email: mario.alviano@gmail.com
Requires-Python: >=3.11,<4.0
Classifier: Programming Language :: Python :: 3
Classifier: Programming Language :: Python :: 3.11
Classifier: Programming Language :: Python :: 3.12
Requires-Dist: distlib (>=0.3.7,<0.4.0)
Requires-Dist: dumbo-asp (>=0.3.6,<0.4.0)
Requires-Dist: pydot (>=1.4.2,<2.0.0)
